chlog/__init__.py
chlog/__main__.py
chlog/changelog.py
chlog/console.py
chlog/versioning.py
chlog/config/__init__.py
chlog/config/alternative.toml
chlog/config/defaults.toml
chlog-0.8.0.dist-info/entry_points.txt
chlog-0.8.0.dist-info/LICENSE
chlog-0.8.0.dist-info/WHEEL
chlog-0.8.0.dist-info/METADATA
chlog-0.8.0.dist-info/RECORD
