Metadata-Version: 2.1
Name: chlog
Version: 0.8.0
Summary: Keep changelogs the easy way
Keywords: cli,console,changelog
Author-email: Ralf Luetkemeier <foss@rlue.de>
Requires-Python: >=3.9,<4
Classifier: Development Status :: 4 - Beta
Classifier: Environment :: Console
Classifier: Intended Audience :: Developers
Classifier: License :: OSI Approved :: MIT License
Classifier: Operating System :: OS Independent
Classifier: Programming Language :: Python :: 3
Classifier: Programming Language :: Python :: 3.8
Classifier: Programming Language :: Python :: 3.9
Classifier: Programming Language :: Python :: 3.10
Classifier: Programming Language :: Python :: 3.11
Classifier: Programming Language :: Python :: 3 :: Only
Classifier: Topic :: Software Development
Classifier: Topic :: Utilities
Requires-Dist: cozyconsole >=0.3.0a2
Requires-Dist: inquirerpy >=0.3.0
Requires-Dist: rich >=13.0.0
Requires-Dist: semver >= 2.13.0
Requires-Dist: tomli >= 2.0.0; python_version < '3.11'
Requires-Dist: flake8 ; extra == "dev"
Requires-Dist: flit ; extra == "dev"
Requires-Dist: pybrownies ; extra == "dev"
Requires-Dist: pylint ; extra == "dev"
Requires-Dist: pytest >=7.2.0 ; extra == "dev"
Requires-Dist: pytest-cov ; extra == "dev"
Requires-Dist: tox ; extra == "dev"
Provides-Extra: dev
